{
    "GPU":{
        "Intel(R) Core(TM) Ultra X9 388H": 122,
        "Intel(R) Core(TM) Ultra X7 368H": 122,
        "Intel(R) Core(TM) Ultra X7 358H": 122,
        "Intel(R) Core(TM) Ultra 9 386H": 40,
        "Intel(R) Core(TM) Ultra 7 366H": 40,
        "Intel(R) Core(TM) Ultra 7 365": 40,
        "Intel(R) Core(TM) Ultra 7 356H": 40,
        "Intel(R) Core(TM) Ultra 7 355": 40,
        "Intel(R) Core(TM) Ultra 5 338H": 98,
        "Intel(R) Core(TM) Ultra 5 336H": 37,
        "Intel(R) Core(TM) Ultra 5 335": 40,
        "Intel(R) Core(TM) Ultra 5 332": 18,
        "Intel(R) Core(TM) Ultra 5 325": 40,
        "Intel(R) Core(TM) Ultra 5 322": 18,
        "Intel(R) Core(TM) Ultra 9 290HX Plus": 8,
        "Intel(R) Core(TM) Ultra 9 288V": 67,
        "Intel(R) Core(TM) Ultra 9 285T": 8,
        "Intel(R) Core(TM) Ultra 9 285K": 8,
        "Intel(R) Core(TM) Ultra 9 285HX": 8,
        "Intel(R) Core(TM) Ultra 9 285H": 77,
        "Intel(R) Core(TM) Ultra 9 285": 8,
        "Intel(R) Core(TM) Ultra 9 275HX": 8,
        "Intel(R) Core(TM) Ultra 7 270K Plus": 8,
        "Intel(R) Core(TM) Ultra 7 270HX Plus": 8,
        "Intel(R) Core(TM) Ultra 7 268V": 66,
        "Intel(R) Core(TM) Ultra 7 266V": 66,
        "Intel(R) Core(TM) Ultra 7 265U": 8,
        "Intel(R) Core(TM) Ultra 7 265T": 8,
        "Intel(R) Core(TM) Ultra 7 265K": 8,
        "Intel(R) Core(TM) Ultra 7 265HX": 8,
        "Intel(R) Core(TM) Ultra 7 265H": 75,
        "Intel(R) Core(TM) Ultra 7 265": 8,
        "Intel(R) Core(TM) Ultra 7 258V": 64,
        "Intel(R) Core(TM) Ultra 7 256V": 64,
        "Intel(R) Core(TM) Ultra 7 255U": 8,
        "Intel(R) Core(TM) Ultra 7 255HX": 8,
        "Intel(R) Core(TM) Ultra 7 255H": 74,
        "Intel(R) Core(TM) Ultra 7 251HX": 6,
        "Intel(R) Core(TM) Ultra 5 250K Plus": 8,
        "Intel(R) Core(TM) Ultra 5 245T": 8,
        "Intel(R) Core(TM) Ultra 5 245K": 8,
        "Intel(R) Core(TM) Ultra 5 245HX": 6,
        "Intel(R) Core(TM) Ultra 5 245": 8,
        "Intel(R) Core(TM) Ultra 5 238V": 53,
        "Intel(R) Core(TM) Ultra 5 236V": 53,
        "Intel(R) Core(TM) Ultra 5 235UA": 8,
        "Intel(R) Core(TM) Ultra 5 235U": 8,
        "Intel(R) Core(TM) Ultra 5 235TA": 6,
        "Intel(R) Core(TM) Ultra 5 235T": 6,
        "Intel(R) Core(TM) Ultra 5 235HX": 6,
        "Intel(R) Core(TM) Ultra 5 235H": 74,
        "Intel(R) Core(TM) Ultra 5 235A": 6,
        "Intel(R) Core(TM) Ultra 5 235": 6,
        "Intel(R) Core(TM) Ultra 5 228V": 53,
        "Intel(R) Core(TM) Ultra 5 226V": 53,
        "Intel(R) Core(TM) Ultra 5 225U": 8,
        "Intel(R) Core(TM) Ultra 5 225T": 4,
        "Intel(R) Core(TM) Ultra 5 225H": 63,
        "Intel(R) Core(TM) Ultra 5 225": 4,
        "Intel(R) Core(TM) Ultra 9 185H": 19,
        "Intel(R) Core(TM) Ultra 7 165H": 19,
        "Intel(R) Core(TM) Ultra 7 155H": 18,
        "Intel(R) Core(TM) Ultra 5 135H": 18,
        "Intel(R) Core(TM) Ultra 5 125H": 18,
        "Intel(R) Core(TM) Ultra 7 165U": 8,
        "Intel(R) Core(TM) Ultra 7 164U": 7,
        "Intel(R) Core(TM) Ultra 7 155U": 8,
        "Intel(R) Core(TM) Ultra 5 135U": 8,
        "Intel(R) Core(TM) Ultra 5 134U": 7
    },
    "NPU":{
        "Intel(R) Core(TM) Ultra X9 388H": 50,
        "Intel(R) Core(TM) Ultra X7 368H": 50,
        "Intel(R) Core(TM) Ultra X7 358H": 50,
        "Intel(R) Core(TM) Ultra 9 386H": 50,
        "Intel(R) Core(TM) Ultra 7 366H": 50,
        "Intel(R) Core(TM) Ultra 7 365": 49,
        "Intel(R) Core(TM) Ultra 7 356H": 50,
        "Intel(R) Core(TM) Ultra 7 355": 49,
        "Intel(R) Core(TM) Ultra 5 338H": 47,
        "Intel(R) Core(TM) Ultra 5 336H": 47,
        "Intel(R) Core(TM) Ultra 5 335": 47,
        "Intel(R) Core(TM) Ultra 5 332": 46,
        "Intel(R) Core(TM) Ultra 5 325": 47,
        "Intel(R) Core(TM) Ultra 5 322": 46,
        "Intel(R) Core(TM) Ultra 9 290HX Plus": 13,
        "Intel(R) Core(TM) Ultra 9 288V": 48,
        "Intel(R) Core(TM) Ultra 9 285T": 13,
        "Intel(R) Core(TM) Ultra 9 285K": 13,
        "Intel(R) Core(TM) Ultra 9 285HX": 13,
        "Intel(R) Core(TM) Ultra 9 285H": 13,
        "Intel(R) Core(TM) Ultra 9 285": 13,
        "Intel(R) Core(TM) Ultra 9 275HX": 13,
        "Intel(R) Core(TM) Ultra 7 270K Plus": 13,
        "Intel(R) Core(TM) Ultra 7 270HX Plus": 13,
        "Intel(R) Core(TM) Ultra 7 268V": 48,
        "Intel(R) Core(TM) Ultra 7 266V": 48,
        "Intel(R) Core(TM) Ultra 7 265U": 12,
        "Intel(R) Core(TM) Ultra 7 265T": 13,
        "Intel(R) Core(TM) Ultra 7 265KF": 13,
        "Intel(R) Core(TM) Ultra 7 265K": 13,
        "Intel(R) Core(TM) Ultra 7 265HX": 13,
        "Intel(R) Core(TM) Ultra 7 265H": 13,
        "Intel(R) Core(TM) Ultra 7 265F": 13,
        "Intel(R) Core(TM) Ultra 7 265": 13,
        "Intel(R) Core(TM) Ultra 7 258V": 47,
        "Intel(R) Core(TM) Ultra 7 256V": 47,
        "Intel(R) Core(TM) Ultra 7 255U": 12,
        "Intel(R) Core(TM) Ultra 7 255HX": 13,
        "Intel(R) Core(TM) Ultra 7 255H": 13,
        "Intel(R) Core(TM) Ultra 7 251HX": 13,
        "Intel(R) Core(TM) Ultra 5 250K Plus": 13,
        "Intel(R) Core(TM) Ultra 5 245T": 13,
        "Intel(R) Core(TM) Ultra 5 245KF": 13,
        "Intel(R) Core(TM) Ultra 5 245K": 13,
        "Intel(R) Core(TM) Ultra 5 245HX": 13,
        "Intel(R) Core(TM) Ultra 5 245": 13,
        "Intel(R) Core(TM) Ultra 5 238V": 40,
        "Intel(R) Core(TM) Ultra 5 236V": 40,
        "Intel(R) Core(TM) Ultra 5 235UA": 12,
        "Intel(R) Core(TM) Ultra 5 235U": 12,
        "Intel(R) Core(TM) Ultra 5 235TA": 13,
        "Intel(R) Core(TM) Ultra 5 235T": 13,
        "Intel(R) Core(TM) Ultra 5 235HX": 13,
        "Intel(R) Core(TM) Ultra 5 235H": 13,
        "Intel(R) Core(TM) Ultra 5 235A": 13,
        "Intel(R) Core(TM) Ultra 5 235": 13,
        "Intel(R) Core(TM) Ultra 5 228V": 40,
        "Intel(R) Core(TM) Ultra 5 226V": 40,
        "Intel(R) Core(TM) Ultra 5 225U": 12,
        "Intel(R) Core(TM) Ultra 5 225T": 13,
        "Intel(R) Core(TM) Ultra 5 225H": 13,
        "Intel(R) Core(TM) Ultra 5 225F": 13,
        "Intel(R) Core(TM) Ultra 5 225": 13,
        "Intel(R) Core(TM) Ultra 9 185H": 11,
        "Intel(R) Core(TM) Ultra 7 165H": 11,
        "Intel(R) Core(TM) Ultra 7 155H": 11,
        "Intel(R) Core(TM) Ultra 5 135H": 11,
        "Intel(R) Core(TM) Ultra 5 125H": 11,
        "Intel(R) Core(TM) Ultra 7 165U": 11,
        "Intel(R) Core(TM) Ultra 7 164U": 11,
        "Intel(R) Core(TM) Ultra 7 155U": 11,
        "Intel(R) Core(TM) Ultra 5 135U": 11,
        "Intel(R) Core(TM) Ultra 5 134U": 11,
        "Intel(R) Core(TM) Ultra 5 125U": 11
    }
}